musicline/__main__.py
musicline-0.1.1.dist-info/licenses/LICENSE
musicline-0.1.1.dist-info/METADATA
musicline-0.1.1.dist-info/WHEEL
musicline-0.1.1.dist-info/top_level.txt
musicline-0.1.1.dist-info/RECORD
