Metadata-Version: 2.4
Name: musicline
Version: 0.1.1
Summary: A music player, but in terminal
Author-email: Mani Arasteh <mani.arasteh92@gmail.com>
License-Expression: MIT
Requires-Python: <4.0.0,>=3.10
License-File: LICENSE
Requires-Dist: textual<3.0.0,>=2.1.2
Requires-Dist: pygame<3.0.0,>=2.6.1
Dynamic: license-file
